MANIFEST.in
README.rst
setup.py
cmsplugin_youtube/__init__.py
cmsplugin_youtube/cms_plugins.py
cmsplugin_youtube/models.py
cmsplugin_youtube/tests.py
cmsplugin_youtube/views.py
cmsplugin_youtube_embed.egg-info/PKG-INFO
cmsplugin_youtube_embed.egg-info/SOURCES.txt
cmsplugin_youtube_embed.egg-info/dependency_links.txt
cmsplugin_youtube_embed.egg-info/top_level.txt