Metadata-Version: 1.0
Name: cmsplugin-youtube-embed
Version: 0.1
Summary: A simple Django app to embed youtube videos into the cms.
Home-page: UNKNOWN
Author: Danie Tate
Author-email: UNKNOWN
License: BSD License
Platform: UNKNOWN
